{
	"name": "CopyTaxiY",
	"properties": {
		"activities": [
			{
				"name": "Copy data",
				"type": "Copy",
				"dependsOn": [],
				"policy": {
					"timeout": "7.00:00:00",
					"retry": 0,
					"retryIntervalInSeconds": 30,
					"secureOutput": false,
					"secureInput": false
				},
				"userProperties": [],
				"typeProperties": {
					"source": {
						"type": "ParquetSource",
						"storeSettings": {
							"type": "AzureBlobStorageReadSettings",
							"recursive": true,
							"wildcardFolderPath": {
								"value": "@concat('yellow/',pipeline().parameters.path)",
								"type": "Expression"
							},
							"wildcardFileName": "*.parquet",
							"enablePartitionDiscovery": false
						}
					},
					"sink": {
						"type": "ParquetSink",
						"storeSettings": {
							"type": "AzureBlobFSWriteSettings",
							"copyBehavior": "MergeFiles"
						},
						"formatSettings": {
							"type": "ParquetWriteSettings"
						}
					},
					"enableStaging": false,
					"translator": {
						"type": "TabularTranslator",
						"typeConversion": true,
						"typeConversionSettings": {
							"allowDataTruncation": true,
							"treatBooleanAsNumber": false
						}
					}
				},
				"inputs": [
					{
						"referenceName": "NYCTaxiY",
						"type": "DatasetReference"
					}
				],
				"outputs": [
					{
						"referenceName": "DataLakeNYCTaxiY",
						"type": "DatasetReference"
					}
				]
			},
			{
				"name": "Data flow1",
				"type": "ExecuteDataFlow",
				"dependsOn": [
					{
						"activity": "Copy data",
						"dependencyConditions": [
							"Succeeded"
						]
					}
				],
				"policy": {
					"timeout": "7.00:00:00",
					"retry": 0,
					"retryIntervalInSeconds": 30,
					"secureOutput": false,
					"secureInput": false
				},
				"userProperties": [],
				"typeProperties": {
					"dataflow": {
						"referenceName": "CopyBlobToSQL",
						"type": "DataFlowReference",
						"parameters": {
							"flield1": "qqq",
							"field1": "['vendorID','doLocationId']"
						}
					},
					"staging": {
						"linkedService": {
							"referenceName": "DataLake",
							"type": "LinkedServiceReference"
						},
						"folderPath": "dls2/stage"
					},
					"compute": {
						"coreCount": 8,
						"computeType": "General"
					},
					"traceLevel": "Fine"
				}
			}
		],
		"parameters": {
			"path": {
				"type": "string"
			}
		},
		"annotations": []
	}
}